{
    "data_list": [
        {
            "date": "2023-01-23",
            "name": "复活节岛上的摩艾石像，智利",
            "url": "/th?id=OHR.SunriseMoai_ZH-CN7413178404_1920x1080.jpg&amp"
        },
        {
            "date": "2023-01-24",
            "name": "多洛米蒂山谷中的科莱圣卢恰小镇，意大利",
            "url": "/th?id=OHR.ColleSantaLucia_ZH-CN7638164714_1920x1080.jpg&amp"
        },
        {
            "date": "2023-01-25",
            "name": "位于阿伯费尔迪桦树林中的罗伯特·彭斯雕像, 苏格兰",
            "url": "/th?id=OHR.BirksofAberfeldy_ZH-CN7810226692_1920x1080.jpg&amp"
        },
        {
            "date": "2023-01-26",
            "name": "天门洞，湖南天门山国家森林公园，中国",
            "url": "/th?id=OHR.HighArchChina_ZH-CN8170154553_1920x1080.jpg&amp"
        },
        {
            "date": "2023-01-27",
            "name": "瓜纳阿卡维韦斯半岛国家公园的红树林，古巴",
            "url": "/th?id=OHR.RedMangrove_ZH-CN4083989028_1920x1080.jpg&amp"
        },
        {
            "date": "2023-01-28",
            "name": "从国际空间站看到的巴哈马周围的蓝绿色水域",
            "url": "/th?id=OHR.BlueBahamas_ZH-CN2083290847_1920x1080.jpg&amp"
        }
    ]
}